arcgis2geojson/__init__.py
arcgis2geojson-3.1.1.dist-info/METADATA
arcgis2geojson-3.1.1.dist-info/WHEEL
arcgis2geojson-3.1.1.dist-info/entry_points.txt
arcgis2geojson-3.1.1.dist-info/licenses/LICENCE
arcgis2geojson-3.1.1.dist-info/RECORD
