Metadata-Version: 2.4
Name: arcgis2geojson
Version: 3.1.1
Summary: A Python library for converting ArcGIS JSON to GeoJSON
License-Expression: MIT
License-File: LICENCE
Author: chris48s
Requires-Python: >=3.10
Classifier: Programming Language :: Python :: 3
Classifier: Programming Language :: Python :: 3.10
Classifier: Programming Language :: Python :: 3.11
Classifier: Programming Language :: Python :: 3.12
Classifier: Programming Language :: Python :: 3.13
Classifier: Programming Language :: Python :: 3.14
Project-URL: Home, https://github.com/chris48s/arcgis2geojson
Project-URL: Source, https://github.com/chris48s/arcgis2geojson
